pandavro/__init__.py
pandavro-1.9.0.dist-info/licenses/LICENSE
pandavro-1.9.0.dist-info/METADATA
pandavro-1.9.0.dist-info/WHEEL
pandavro-1.9.0.dist-info/top_level.txt
pandavro-1.9.0.dist-info/RECORD
